psik_api/__init__.py
psik_api/authz.py
psik_api/config.py
psik_api/dependencies.py
psik_api/internal/paths.py
psik_api/internal/tasks.py
psik_api/main.py
psik_api/models.py
psik_api/routers/__init__.py
psik_api/routers/backends.py
psik_api/routers/callback.py
psik_api/routers/inputs.py
psik_api/routers/jobs.py
psik_api/routers/outputs.py
psik_api-1.0.0.dist-info/LICENSE
psik_api-1.0.0.dist-info/METADATA
psik_api-1.0.0.dist-info/WHEEL
psik_api-1.0.0.dist-info/RECORD
