Metadata-Version: 2.1
Name: psik_api
Version: 1.0.0
Summary: API for a portable submission interface for batch jobs.
Home-page: https://frobnitzem.github.io/psik_api
License: BSD-3-Clause
Author: David M. Rogers
Author-email: predictivestatmech@gmail.com
Requires-Python: >=3.9,<4.0
Classifier: License :: OSI Approved :: BSD License
Classifier: Programming Language :: Python :: 3
Classifier: Programming Language :: Python :: 3.9
Classifier: Programming Language :: Python :: 3.10
Classifier: Programming Language :: Python :: 3.11
Classifier: Programming Language :: Python :: 3.12
Requires-Dist: aiohttp (>=3.8.5)
Requires-Dist: certified (>=0.10,<2.0)
Requires-Dist: fastapi (>=0.101.1,<0.102.0)
Requires-Dist: importlib-metadata (>=6.8.0,<7.0.0)
Requires-Dist: psik (>=1.3.0,<2.0)
Requires-Dist: python-multipart (>=0.0.6,<0.0.7)
Requires-Dist: sqlalchemy (>=2.0.36,<3.0.0)
Requires-Dist: uvicorn (>=0.23.2,<0.24.0)
Project-URL: Repository, https://github.com/frobnitzem/psik_api
